[{"_id":"c34f95d5-4d41-4472-962f-7013cbae6bab","name":"Mat Muhly","address":{"streetName":"77 Moulton Park","streetNumber":"65449","neighborhood":"Pearson","city":"Mar de Plata","state":"buenos aires","country":"Argentina","coordinates":{"latitud":-38.018952,"longitud":-57.564474}},"images":"http://dummyimage.com/180x100.png/dddddd/000000","contact":{"phoneNumber":"859-530-9982","email":"apartleton0@ucsd.edu","socialMedia":{"instagram":"rclaiton0@youtube.com","facebook":"ediggle0@google.nl","wpp":"clemarchand0@paginegialle.it"}},"tables":1,"schedule":"1/29/2023","menu":"pede","diets":"congue etiam","paymentMethods":"visa","atmosphere":"dapibus","extras":{"id":1,"name":"petfriendly"},"room":"terrace","active":true},
{"_id":"3c7d5bf9-9f81-4ef9-88a9-6884e0ad4aba","name":"Cartilage Lichen","address":{"streetName":"7560 Packers Place","streetNumber":"9","neighborhood":"Hooker","city":"Mar de Plata","state":"buenos aires","country":"Argentina","coordinates":{"latitud":-38.007939,"longitud":-57.556283}},"images":"http://dummyimage.com/200x100.png/cc0000/ffffff","contact":{"phoneNumber":"113-538-8519","email":"icoffee1@gravatar.com","socialMedia":{"instagram":"eblissett1@e-recht24.de","facebook":"kformby1@printfriendly.com","wpp":"atimothy1@un.org"}},"tables":2,"schedule":"11/16/2022","menu":"eu","diets":"id lobortis","paymentMethods":"jcb","atmosphere":"cras","extras":{"id":2,"name":"petfriendly"},"room":"Indoor","active":true},
{"_id":"bd65da05-6eab-4ae5-9c33-0aafa63d2aef","name":"Bear Huckleberry","address":{"streetName":"3 Becker Place","streetNumber":"10","neighborhood":"Armistice","city":"Mar de Plata","state":"buenos aires","country":"Argentina","coordinates":{"latitud":-37.995769,"longitud":-57.546435}},"images":"http://dummyimage.com/158x100.png/dddddd/000000","contact":{"phoneNumber":"371-180-6419","email":"iverdon2@vistaprint.com","socialMedia":{"instagram":"asalliss2@weebly.com","facebook":"bharling2@answers.com","wpp":"jcarnalan2@nymag.com"}},"tables":3,"schedule":"11/5/2022","menu":"sit","diets":"vitae nisl","paymentMethods":"jcb","atmosphere":"sapien","extras":{"id":3,"name":"happyhour"},"room":"bar","active":false},
{"_id":"4464cceb-222a-4791-81dd-b7f7bf1bf2d3","name":"Hooded Coralroot","address":{"streetName":"58 Rusk Trail","streetNumber":"09342","neighborhood":"Express","city":"Mar de Plata","state":"buenos aires","country":"Argentina","coordinates":{"latitud":-37.991992,"longitud":-57.543345}},"images":"http://dummyimage.com/176x100.png/cc0000/ffffff","contact":{"phoneNumber":"616-919-7659","email":"egregolin3@omniture.com","socialMedia":{"instagram":"rstyle3@tiny.cc","facebook":"aackeroyd3@nifty.com","wpp":"rchudleigh3@samsung.com"}},"tables":4,"schedule":"5/4/2022","menu":"nisl","diets":"leo maecenas","paymentMethods":"diners-club-enroute","atmosphere":"consectetuer","extras":{"id":4,"name":"petfriendly"},"room":"bar","active":true},
{"_id":"efb157dd-10db-4e99-a17f-8835534f85bd","name":"Ticktrefoil","address":{"streetName":"40 Village Park","streetNumber":"6","neighborhood":"Ludington","city":"Mar de Plata","state":"buenos aires","country":"Argentina","coordinates":{"latitud":-38.006543,"longitud":-57.547411}},"images":"http://dummyimage.com/120x100.png/cc0000/ffffff","contact":{"phoneNumber":"344-668-8974","email":"rkettlesing4@opera.com","socialMedia":{"instagram":"jmill4@dagondesign.com","facebook":"rangelini4@printfriendly.com","wpp":"iohanley4@homestead.com"}},"tables":5,"schedule":"1/9/2023","menu":"est","diets":"cum sociis","paymentMethods":"jcb","atmosphere":"vel","extras":{"id":5,"name":"petfriendly"},"room":"Indoor","active":true},
{"_id":"922ec23e-4d94-4c58-863a-f8c6fc77522a","name":"Murta","address":{"streetName":"8 2nd Trail","streetNumber":"9","neighborhood":"Lake View","city":"Mar de Plata","state":"buenos aires","country":"Argentina","coordinates":{"latitud":-38.005218,"longitud":-57.560344}},"images":"http://dummyimage.com/162x100.png/ff4444/ffffff","contact":{"phoneNumber":"720-944-1873","email":"mbrockley5@senate.gov","socialMedia":{"instagram":"nkearley5@ehow.com","facebook":"rjerzycowski5@chron.com","wpp":"psalmen5@geocities.jp"}},"tables":6,"schedule":"12/12/2022","menu":"id","diets":"vestibulum ac","paymentMethods":"jcb","atmosphere":"placerat","extras":{"id":6,"name":"petfriendly"},"room":"outdoor","active":true},
{"_id":"a2b096d6-a383-46df-b2e6-20d8cede7edf","name":"Roughhairy Maiden Fern","address":{"streetName":"636 Badeau Terrace","streetNumber":"9","neighborhood":"Columbus","city":"Mar de Plata","state":"buenos aires","country":"Argentina","coordinates":{"latitud":-38.000225,"longitud":-57.550673}},"images":"http://dummyimage.com/148x100.png/dddddd/000000","contact":{"phoneNumber":"237-832-1778","email":"hhugenin6@ed.gov","socialMedia":{"instagram":"mrizzone6@dion.ne.jp","facebook":"aterrell6@about.com","wpp":"gben6@de.vu"}},"tables":7,"schedule":"9/1/2022","menu":"justo","diets":"turpis elementum","paymentMethods":"jcb","atmosphere":"donec","extras":{"id":7,"name":"smoke"},"room":"terrace","active":false},
{"_id":"9b1e2b73-6260-447f-a58b-dd6a69875c9f","name":"Myelochroa Lichen","address":{"streetName":"10081 Main Place","streetNumber":"63","neighborhood":"Springs","city":"Mar de Plata","state":"buenos aires","country":"Argentina","coordinates":{"latitud":-38.016961,"longitud":-57.54803}},"images":"http://dummyimage.com/231x100.png/dddddd/000000","contact":{"phoneNumber":"454-796-7552","email":"jducastel7@apache.org","socialMedia":{"instagram":"trobins7@dmoz.org","facebook":"mantoniades7@bing.com","wpp":"owrey7@globo.com"}},"tables":8,"schedule":"7/11/2022","menu":"diam","diets":"nunc rhoncus","paymentMethods":"maestro","atmosphere":"odio","extras":{"id":8,"name":"happyhour"},"room":"hall","active":false},
{"_id":"c8d76001-ea1e-4966-a3d4-e40c1d1b0e32","name":"Willowleaf Yellowhead","address":{"streetName":"72957 Grasskamp Parkway","streetNumber":"4","neighborhood":"Crownhardt","city":"Mar de Plata","state":"buenos aires","country":"Argentina","coordinates":{"latitud":-38.013291,"longitud":-57.566649}},"images":"http://dummyimage.com/130x100.png/ff4444/ffffff","contact":{"phoneNumber":"171-283-8069","email":"sarnoll8@51.la","socialMedia":{"instagram":"nmuttitt8@unc.edu","facebook":"sponsford8@livejournal.com","wpp":"arusson8@scribd.com"}},"tables":9,"schedule":"3/28/2022","menu":"quis","diets":"nunc nisl","paymentMethods":"laser","atmosphere":"odio","extras":{"id":9,"name":"smoke"},"room":"hall","active":true},
{"_id":"245f6699-9cb1-4857-a403-eee7e0057782","name":"Grass-leaved Rock Goldenrod","address":{"streetName":"5128 Spohn Terrace","streetNumber":"2504","neighborhood":"Cody","city":"Mar de Plata","state":"buenos aires","country":"Argentina","coordinates":{"latitud":-38.020199,"longitud":-57.546625}},"images":"http://dummyimage.com/144x100.png/dddddd/000000","contact":{"phoneNumber":"885-196-2507","email":"atopper9@typepad.com","socialMedia":{"instagram":"salywin9@4shared.com","facebook":"boldershaw9@wikispaces.com","wpp":"kteresia9@geocities.jp"}},"tables":10,"schedule":"10/10/2022","menu":"magna","diets":"ante ipsum","paymentMethods":"mastercard","atmosphere":"sed","extras":{"id":10,"name":"happyhour"},"room":"outdoor","active":false},
{"_id":"5cae45c7-c70e-4844-837c-a996e0ab6dbe","name":"Acisanthera","address":{"streetName":"77335 Forster Parkway","streetNumber":"7319","neighborhood":"Karstens","city":"Mar de Plata","state":"buenos aires","country":"Argentina","coordinates":{"latitud":-37.9835,"longitud":-57.56239}},"images":"http://dummyimage.com/202x100.png/5fa2dd/ffffff","contact":{"phoneNumber":"794-194-8291","email":"wmoreta@homestead.com","socialMedia":{"instagram":"lcalvera@webeden.co.uk","facebook":"ggianettia@flavors.me","wpp":"mmarkiea@berkeley.edu"}},"tables":11,"schedule":"12/4/2022","menu":"mus","diets":"dapibus augue","paymentMethods":"americanexpress","atmosphere":"in","extras":{"id":11,"name":"happyhour"},"room":"outdoor","active":true},
{"_id":"8f787b27-6994-4418-993c-95abea6468d7","name":"Sawtooth Candyleaf","address":{"streetName":"14591 Cascade Crossing","streetNumber":"42","neighborhood":"Golf","city":"Mar de Plata","state":"buenos aires","country":"Argentina","coordinates":{"latitud":-37.988449,"longitud":-57.563518}},"images":"http://dummyimage.com/155x100.png/ff4444/ffffff","contact":{"phoneNumber":"375-955-2549","email":"wjobinb@squarespace.com","socialMedia":{"instagram":"bcleminshawb@woothemes.com","facebook":"qdimockb@woothemes.com","wpp":"mletchmoreb@hhs.gov"}},"tables":12,"schedule":"9/27/2022","menu":"odio","diets":"vel est","paymentMethods":"diners-club-enroute","atmosphere":"leo","extras":{"id":12,"name":"petfriendly"},"room":"Indoor","active":false},
{"_id":"236e2aa1-7345-44e3-8f33-aff32005ffda","name":"Guinea Bactris","address":{"streetName":"7297 Prentice Plaza","streetNumber":"47","neighborhood":"Beilfuss","city":"Mar de Plata","state":"buenos aires","country":"Argentina","coordinates":{"latitud":-38.016102,"longitud":-57.570226}},"images":"http://dummyimage.com/165x100.png/ff4444/ffffff","contact":{"phoneNumber":"799-917-1368","email":"atumininic@cam.ac.uk","socialMedia":{"instagram":"gcantuac@discuz.net","facebook":"ablazhevichc@narod.ru","wpp":"mcuerdallc@shinystat.com"}},"tables":13,"schedule":"1/18/2023","menu":"quis","diets":"curae donec","paymentMethods":"jcb","atmosphere":"dolor","extras":{"id":13,"name":"happyhour"},"room":"terrace","active":true},
{"_id":"2cedeb45-d591-40a2-ab4e-5bce71f79c26","name":"Morinda Spruce","address":{"streetName":"8 Park Meadow Plaza","streetNumber":"308","neighborhood":"Kinsman","city":"Mar de Plata","state":"buenos aires","country":"Argentina","coordinates":{"latitud":-37.993319,"longitud":-57.568219}},"images":"http://dummyimage.com/173x100.png/ff4444/ffffff","contact":{"phoneNumber":"475-840-3960","email":"msebired@live.com","socialMedia":{"instagram":"trhydderchd@myspace.com","facebook":"gschlaghd@webeden.co.uk","wpp":"apesslerd@phpbb.com"}},"tables":14,"schedule":"7/21/2022","menu":"felis","diets":"augue vestibulum","paymentMethods":"diners-club-enroute","atmosphere":"aliquet","extras":{"id":14,"name":"petfriendly"},"room":"outdoor","active":true},
{"_id":"aff0954d-1fbd-4f00-a021-44ec29b85b7f","name":"Pinto Beardtongue","address":{"streetName":"7083 Saint Paul Avenue","streetNumber":"85","neighborhood":"Kedzie","city":"Mar de Plata","state":"buenos aires","country":"Argentina","coordinates":{"latitud":-37.991361,"longitud":-57.567935}},"images":"http://dummyimage.com/211x100.png/5fa2dd/ffffff","contact":{"phoneNumber":"446-878-6890","email":"nkenwelle@hugedomains.com","socialMedia":{"instagram":"cleadere@jigsy.com","facebook":"dfodene@microsoft.com","wpp":"cebbine@epa.gov"}},"tables":15,"schedule":"7/14/2022","menu":"lacus","diets":"ut erat","paymentMethods":"jcb","atmosphere":"pharetra","extras":{"id":15,"name":"smoke"},"room":"outdoor","active":false},
{"_id":"4b16ff66-71ac-4d2f-94c6-7568dcb23064","name":"Cutleaf Waterparsnip","address":{"streetName":"19811 Alpine Parkway","streetNumber":"75","neighborhood":"Evergreen","city":"Mar de Plata","state":"buenos aires","country":"Argentina","coordinates":{"latitud":-38.004669,"longitud":-57.545258}},"images":"http://dummyimage.com/187x100.png/cc0000/ffffff","contact":{"phoneNumber":"357-678-1342","email":"dchetwindf@google.de","socialMedia":{"instagram":"svanhaeftenf@hibu.com","facebook":"erumbellowf@wikimedia.org","wpp":"dpurplef@ask.com"}},"tables":16,"schedule":"1/16/2023","menu":"nulla","diets":"felis sed","paymentMethods":"jcb","atmosphere":"fusce","extras":{"id":16,"name":"happyhour"},"room":"Indoor","active":false},
{"_id":"90b01901-5b97-4ddd-a695-f294e02d508d","name":"Adam's Tree","address":{"streetName":"1059 Dixon Way","streetNumber":"298","neighborhood":"Johnson","city":"Mar de Plata","state":"buenos aires","country":"Argentina","coordinates":{"latitud":-38.019094,"longitud":-57.56355}},"images":"http://dummyimage.com/191x100.png/5fa2dd/ffffff","contact":{"phoneNumber":"446-810-9586","email":"gboultong@cloudflare.com","socialMedia":{"instagram":"rdagong@last.fm","facebook":"vstoakleyg@tamu.edu","wpp":"bbartalettig@prlog.org"}},"tables":17,"schedule":"5/15/2022","menu":"luctus","diets":"sit amet","paymentMethods":"mastercard","atmosphere":"massa","extras":{"id":17,"name":"petfriendly"},"room":"bar","active":false},
{"_id":"e57211a0-1e6f-4de0-a42c-d6c8ada413c4","name":"Widethroat Yellow Monkeyflower","address":{"streetName":"6476 Northview Trail","streetNumber":"29","neighborhood":"Fairview","city":"Mar de Plata","state":"buenos aires","country":"Argentina","coordinates":{"latitud":-38.018138,"longitud":-57.552234}},"images":"http://dummyimage.com/102x100.png/ff4444/ffffff","contact":{"phoneNumber":"905-527-3171","email":"vperilloh@meetup.com","socialMedia":{"instagram":"sweineh@friendfeed.com","facebook":"gclarkewilliamsh@a8.net","wpp":"bdevoteh@shop-pro.jp"}},"tables":18,"schedule":"12/20/2022","menu":"ac","diets":"morbi quis","paymentMethods":"jcb","atmosphere":"in","extras":{"id":18,"name":"petfriendly"},"room":"terrace","active":false},
{"_id":"ea393f41-e6bc-455c-8621-27cc85dcfb24","name":"Sonoran Maiden Fern","address":{"streetName":"419 Corben Park","streetNumber":"493","neighborhood":"Holmberg","city":"Mar de Plata","state":"buenos aires","country":"Argentina","coordinates":{"latitud":-38.011675,"longitud":-57.556263}},"images":"http://dummyimage.com/120x100.png/dddddd/000000","contact":{"phoneNumber":"230-500-3405","email":"oyeabsleyi@digg.com","socialMedia":{"instagram":"fbrassingtoni@quantcast.com","facebook":"kmohringi@cpanel.net","wpp":"bvongladbachi@dot.gov"}},"tables":19,"schedule":"3/13/2023","menu":"suscipit","diets":"sapien arcu","paymentMethods":"jcb","atmosphere":"morbi","extras":{"id":19,"name":"petfriendly"},"room":"terrace","active":true},
{"_id":"c7771510-b1dc-4b5e-95b6-0cda811de9d0","name":"Carlott's Violet","address":{"streetName":"772 Tennyson Trail","streetNumber":"7","neighborhood":"Sugar","city":"Mar de Plata","state":"buenos aires","country":"Argentina","coordinates":{"latitud":-38.007431,"longitud":-57.553818}},"images":"http://dummyimage.com/236x100.png/dddddd/000000","contact":{"phoneNumber":"507-585-5623","email":"dyusupovj@comsenz.com","socialMedia":{"instagram":"lskehensj@ucla.edu","facebook":"mleyntonj@cbc.ca","wpp":"emonroj@hostgator.com"}},"tables":20,"schedule":"1/31/2023","menu":"velit","diets":"id turpis","paymentMethods":"mastercard","atmosphere":"magnis","extras":{"id":20,"name":"happyhour"},"room":"hall","active":true},
{"_id":"28a67685-d7eb-4f0d-a572-7270b414c2c3","name":"Star Duckweed","address":{"streetName":"17 Mallory Center","streetNumber":"03366","neighborhood":"Loeprich","city":"Mar de Plata","state":"buenos aires","country":"Argentina","coordinates":{"latitud":-38.008133,"longitud":-57.567516}},"images":"http://dummyimage.com/177x100.png/dddddd/000000","contact":{"phoneNumber":"696-241-4049","email":"cpitcaithlyk@slashdot.org","socialMedia":{"instagram":"hdeekk@last.fm","facebook":"lheynsk@skype.com","wpp":"dhasslocherk@businesswire.com"}},"tables":21,"schedule":"9/12/2022","menu":"mauris","diets":"eget eros","paymentMethods":"bankcard","atmosphere":"ut","extras":{"id":21,"name":"smoke"},"room":"terrace","active":true},
{"_id":"6a609436-879d-466c-968e-aa0b89b3be5f","name":"Thunberg's Geranium","address":{"streetName":"9 Dixon Junction","streetNumber":"199","neighborhood":"Linden","city":"Mar de Plata","state":"buenos aires","country":"Argentina","coordinates":{"latitud":-37.99391,"longitud":-57.555494}},"images":"http://dummyimage.com/227x100.png/ff4444/ffffff","contact":{"phoneNumber":"136-185-3954","email":"rdorrelll@i2i.jp","socialMedia":{"instagram":"kbonehilll@pinterest.com","facebook":"dattlel@google.ru","wpp":"dredingl@technorati.com"}},"tables":22,"schedule":"11/1/2022","menu":"in","diets":"nullam molestie","paymentMethods":"visa-electron","atmosphere":"ipsum","extras":{"id":22,"name":"happyhour"},"room":"hall","active":true},
{"_id":"46116fb1-a4d0-4672-81ed-2c27abc48c2d","name":"Bladderwort","address":{"streetName":"899 Grayhawk Lane","streetNumber":"2534","neighborhood":"Carpenter","city":"Mar de Plata","state":"buenos aires","country":"Argentina","coordinates":{"latitud":-37.983665,"longitud":-57.570385}},"images":"http://dummyimage.com/221x100.png/dddddd/000000","contact":{"phoneNumber":"404-297-7770","email":"kkeedym@hud.gov","socialMedia":{"instagram":"wchampkinm@comsenz.com","facebook":"acockranm@amazon.de","wpp":"mneubiginm@ask.com"}},"tables":23,"schedule":"8/15/2022","menu":"tortor","diets":"praesent blandit","paymentMethods":"maestro","atmosphere":"nunc","extras":{"id":23,"name":"smoke"},"room":"Indoor","active":false},
{"_id":"731bb539-87c7-44c2-96b4-7fa44a2f5ef7","name":"Papaya","address":{"streetName":"900 Dawn Junction","streetNumber":"1288","neighborhood":"Melrose","city":"Mar de Plata","state":"buenos aires","country":"Argentina","coordinates":{"latitud":-37.992399,"longitud":-57.569326}},"images":"http://dummyimage.com/155x100.png/ff4444/ffffff","contact":{"phoneNumber":"339-298-8992","email":"hbeavann@a8.net","socialMedia":{"instagram":"eburnhamn@google.it","facebook":"aesherwoodn@cafepress.com","wpp":"bcavann@patch.com"}},"tables":24,"schedule":"5/19/2022","menu":"sem","diets":"dui nec","paymentMethods":"jcb","atmosphere":"sem","extras":{"id":24,"name":"happyhour"},"room":"Indoor","active":false},
{"_id":"9ae9aca6-468d-4184-8405-1baa6dbc4a1b","name":"Trinity Buckwheat","address":{"streetName":"1761 Muir Hill","streetNumber":"6794","neighborhood":"Doe Crossing","city":"Mar de Plata","state":"buenos aires","country":"Argentina","coordinates":{"latitud":-38.009964,"longitud":-57.570507}},"images":"http://dummyimage.com/239x100.png/dddddd/000000","contact":{"phoneNumber":"812-456-5653","email":"ocysono@123-reg.co.uk","socialMedia":{"instagram":"cdowso@mayoclinic.com","facebook":"ftriggolo@gravatar.com","wpp":"tabrahamso@etsy.com"}},"tables":25,"schedule":"9/7/2022","menu":"imperdiet","diets":"enim sit","paymentMethods":"jcb","atmosphere":"commodo","extras":{"id":25,"name":"petfriendly"},"room":"Indoor","active":true},
{"_id":"2155d1df-0b06-49fa-8b02-185a3d0f3e1f","name":"Pacific Silver Fir","address":{"streetName":"92023 Old Shore Street","streetNumber":"94","neighborhood":"Thierer","city":"Mar de Plata","state":"buenos aires","country":"Argentina","coordinates":{"latitud":-38.007449,"longitud":-57.56028}},"images":"http://dummyimage.com/229x100.png/ff4444/ffffff","contact":{"phoneNumber":"126-127-6098","email":"nvictoryp@angelfire.com","socialMedia":{"instagram":"bcrowchp@soup.io","facebook":"msalernop@nba.com","wpp":"afuzzeyp@barnesandnoble.com"}},"tables":26,"schedule":"11/30/2022","menu":"augue","diets":"congue vivamus","paymentMethods":"jcb","atmosphere":"lobortis","extras":{"id":26,"name":"petfriendly"},"room":"outdoor","active":true},
{"_id":"2e4e74af-4b40-4ee0-ad89-4bf14594aa09","name":"Heartleaf Bittercress","address":{"streetName":"44 Nova Junction","streetNumber":"7300","neighborhood":"Vidon","city":"Mar de Plata","state":"buenos aires","country":"Argentina","coordinates":{"latitud":-37.991361,"longitud":-57.55402}},"images":"http://dummyimage.com/216x100.png/cc0000/ffffff","contact":{"phoneNumber":"920-262-6750","email":"gkarolczykq@theatlantic.com","socialMedia":{"instagram":"hprinneq@t-online.de","facebook":"mwentworthq@scribd.com","wpp":"ltaschq@pcworld.com"}},"tables":27,"schedule":"1/29/2023","menu":"velit","diets":"justo etiam","paymentMethods":"jcb","atmosphere":"tempor","extras":{"id":27,"name":"petfriendly"},"room":"outdoor","active":false},
{"_id":"dcb7dee2-d88e-452e-8fc2-9d5f8bde1f5e","name":"Showy Dandelion","address":{"streetName":"2 Kenwood Junction","streetNumber":"3818","neighborhood":"Northland","city":"Mar de Plata","state":"buenos aires","country":"Argentina","coordinates":{"latitud":-38.004872,"longitud":-57.553909}},"images":"http://dummyimage.com/124x100.png/cc0000/ffffff","contact":{"phoneNumber":"574-384-0129","email":"cmacfadzeanr@census.gov","socialMedia":{"instagram":"omatevosianr@google.cn","facebook":"gsapsedr@cisco.com","wpp":"ksparker@amazon.com"}},"tables":28,"schedule":"4/19/2022","menu":"volutpat","diets":"lacus at","paymentMethods":"mastercard","atmosphere":"volutpat","extras":{"id":28,"name":"smoke"},"room":"hall","active":true},
{"_id":"c6c9a1e4-e465-489b-baf6-15368a10bce4","name":"Silver-leaf Ironbark","address":{"streetName":"95677 Golf View Hill","streetNumber":"0","neighborhood":"Michigan","city":"Mar de Plata","state":"buenos aires","country":"Argentina","coordinates":{"latitud":-38.016258,"longitud":-57.564541}},"images":"http://dummyimage.com/177x100.png/5fa2dd/ffffff","contact":{"phoneNumber":"244-490-7644","email":"schalleners@sakura.ne.jp","socialMedia":{"instagram":"gmcenerys@wikispaces.com","facebook":"btooths@amazonaws.com","wpp":"ewhortons@thetimes.co.uk"}},"tables":29,"schedule":"6/25/2022","menu":"vestibulum","diets":"vel augue","paymentMethods":"laser","atmosphere":"enim","extras":{"id":29,"name":"petfriendly"},"room":"outdoor","active":true},
{"_id":"06e735cb-2de0-456e-9b47-4b7a5855d7e5","name":"Lemon Thyme","address":{"streetName":"7127 Aberg Circle","streetNumber":"782","neighborhood":"Truax","city":"Mar de Plata","state":"buenos aires","country":"Argentina","coordinates":{"latitud":-37.983967,"longitud":-57.565087}},"images":"http://dummyimage.com/231x100.png/dddddd/000000","contact":{"phoneNumber":"843-968-3212","email":"wcockadayt@auda.org.au","socialMedia":{"instagram":"rmacnesst@miibeian.gov.cn","facebook":"qrecket@wisc.edu","wpp":"tmcmylort@constantcontact.com"}},"tables":30,"schedule":"1/6/2023","menu":"velit","diets":"hac habitasse","paymentMethods":"china-unionpay","atmosphere":"duis","extras":{"id":30,"name":"happyhour"},"room":"terrace","active":false},
{"_id":"b6ad1fe0-d789-4b63-ad6c-4ed21a558025","name":"Alvord Milkvetch","address":{"streetName":"37 Eagan Street","streetNumber":"7","neighborhood":"Dryden","city":"Mar de Plata","state":"buenos aires","country":"Argentina","coordinates":{"latitud":-38.019419,"longitud":-57.552638}},"images":"http://dummyimage.com/159x100.png/5fa2dd/ffffff","contact":{"phoneNumber":"688-867-0785","email":"gandreiau@digg.com","socialMedia":{"instagram":"rcapeu@mit.edu","facebook":"mdenajerau@engadget.com","wpp":"jblenkinsopu@smh.com.au"}},"tables":31,"schedule":"6/9/2022","menu":"cum","diets":"eu massa","paymentMethods":"china-unionpay","atmosphere":"tempus","extras":{"id":31,"name":"petfriendly"},"room":"terrace","active":true},
{"_id":"adfcae2f-1e74-4865-af96-86aa403f212d","name":"White Fairypoppy","address":{"streetName":"85 Huxley Way","streetNumber":"77","neighborhood":"Fieldstone","city":"Mar de Plata","state":"buenos aires","country":"Argentina","coordinates":{"latitud":-37.987741,"longitud":-57.551702}},"images":"http://dummyimage.com/149x100.png/ff4444/ffffff","contact":{"phoneNumber":"821-722-3179","email":"vhallgathv@europa.eu","socialMedia":{"instagram":"jtizzardv@about.me","facebook":"spontv@mozilla.org","wpp":"fdavleyv@freewebs.com"}},"tables":32,"schedule":"2/18/2023","menu":"eget","diets":"tortor quis","paymentMethods":"jcb","atmosphere":"mauris","extras":{"id":32,"name":"happyhour"},"room":"bar","active":true},
{"_id":"f0f190c3-c049-4d95-ae48-4c6e764f55e2","name":"Casia Amarilla","address":{"streetName":"32 Goodland Terrace","streetNumber":"5","neighborhood":"Morningstar","city":"Mar de Plata","state":"buenos aires","country":"Argentina","coordinates":{"latitud":-38.011527,"longitud":-57.567956}},"images":"http://dummyimage.com/136x100.png/5fa2dd/ffffff","contact":{"phoneNumber":"878-859-0867","email":"yvaderw@goodreads.com","socialMedia":{"instagram":"bpeatw@aboutads.info","facebook":"dpendreighw@taobao.com","wpp":"bbelchambersw@home.pl"}},"tables":33,"schedule":"12/22/2022","menu":"sapien","diets":"turpis enim","paymentMethods":"jcb","atmosphere":"rhoncus","extras":{"id":33,"name":"happyhour"},"room":"terrace","active":true},
{"_id":"4365d21d-6724-4b0b-bdd7-6054cff4e59a","name":"Oahu Riverhemp","address":{"streetName":"0642 Ramsey Junction","streetNumber":"429","neighborhood":"Elgar","city":"Mar de Plata","state":"buenos aires","country":"Argentina","coordinates":{"latitud":-37.997037,"longitud":-57.558322}},"images":"http://dummyimage.com/135x100.png/5fa2dd/ffffff","contact":{"phoneNumber":"140-354-1064","email":"hserlex@house.gov","socialMedia":{"instagram":"hcaffx@networksolutions.com","facebook":"pgallardox@mtv.com","wpp":"dtewelsonx@livejournal.com"}},"tables":34,"schedule":"11/19/2022","menu":"non","diets":"congue vivamus","paymentMethods":"switch","atmosphere":"nulla","extras":{"id":34,"name":"happyhour"},"room":"hall","active":true},
{"_id":"e8e58e4c-0e70-4497-be54-c87baa042eb4","name":"Appalachian Rhizomnium Moss","address":{"streetName":"81884 Chinook Park","streetNumber":"61","neighborhood":"Onsgard","city":"Mar de Plata","state":"buenos aires","country":"Argentina","coordinates":{"latitud":-37.985593,"longitud":-57.571379}},"images":"http://dummyimage.com/114x100.png/5fa2dd/ffffff","contact":{"phoneNumber":"299-256-8257","email":"kalgary@ed.gov","socialMedia":{"instagram":"ctommasuzziy@cloudflare.com","facebook":"cdingy@ifeng.com","wpp":"wstratleyy@telegraph.co.uk"}},"tables":35,"schedule":"11/17/2022","menu":"curabitur","diets":"vel ipsum","paymentMethods":"jcb","atmosphere":"ut","extras":{"id":35,"name":"smoke"},"room":"Indoor","active":false},
{"_id":"e42dae87-869d-44e3-aa2a-f58f7895a3a0","name":"Gooseberry Geranium","address":{"streetName":"07150 Upham Circle","streetNumber":"06898","neighborhood":"Village Green","city":"Mar de Plata","state":"buenos aires","country":"Argentina","coordinates":{"latitud":-38.002688,"longitud":-57.546307}},"images":"http://dummyimage.com/139x100.png/cc0000/ffffff","contact":{"phoneNumber":"154-858-1618","email":"bchastaingz@craigslist.org","socialMedia":{"instagram":"bsporlez@purevolume.com","facebook":"ekohenz@tuttocitta.it","wpp":"jjanuz@jalbum.net"}},"tables":36,"schedule":"8/18/2022","menu":"dictumst","diets":"volutpat dui","paymentMethods":"jcb","atmosphere":"in","extras":{"id":36,"name":"smoke"},"room":"hall","active":true},
{"_id":"e6cecba7-c7e3-4635-ab92-83de02f2c272","name":"Lemmon's Cinquefoil","address":{"streetName":"00087 Declaration Trail","streetNumber":"7","neighborhood":"Huxley","city":"Mar de Plata","state":"buenos aires","country":"Argentina","coordinates":{"latitud":-38.005289,"longitud":-57.55611}},"images":"http://dummyimage.com/244x100.png/cc0000/ffffff","contact":{"phoneNumber":"925-162-9916","email":"gmurtagh10@taobao.com","socialMedia":{"instagram":"kfellos10@amazon.co.jp","facebook":"glabes10@nyu.edu","wpp":"nduval10@drupal.org"}},"tables":37,"schedule":"12/9/2022","menu":"in","diets":"justo sollicitudin","paymentMethods":"jcb","atmosphere":"phasellus","extras":{"id":37,"name":"petfriendly"},"room":"hall","active":false},
{"_id":"766a1fdf-1ce9-4157-b200-5edd861482d4","name":"Tea","address":{"streetName":"4811 Bluejay Street","streetNumber":"79","neighborhood":"Eagan","city":"Mar de Plata","state":"buenos aires","country":"Argentina","coordinates":{"latitud":-38.006,"longitud":-57.563688}},"images":"http://dummyimage.com/108x100.png/dddddd/000000","contact":{"phoneNumber":"518-780-4879","email":"gstearndale11@ocn.ne.jp","socialMedia":{"instagram":"eburn11@netlog.com","facebook":"cstreatfield11@google.nl","wpp":"tbrimner11@mozilla.com"}},"tables":38,"schedule":"3/17/2023","menu":"diam","diets":"risus praesent","paymentMethods":"visa-electron","atmosphere":"justo","extras":{"id":38,"name":"happyhour"},"room":"bar","active":false},
{"_id":"c06d5c59-0bc7-43df-95bb-29d47ce3c3ed","name":"Lichenothelia Lichen","address":{"streetName":"891 Dakota Street","streetNumber":"3","neighborhood":"Cascade","city":"Mar de Plata","state":"buenos aires","country":"Argentina","coordinates":{"latitud":-37.995464,"longitud":-57.562464}},"images":"http://dummyimage.com/224x100.png/cc0000/ffffff","contact":{"phoneNumber":"996-994-2498","email":"abockh12@flavors.me","socialMedia":{"instagram":"amarkova12@loc.gov","facebook":"kboyde12@free.fr","wpp":"rhugin12@adobe.com"}},"tables":39,"schedule":"5/23/2022","menu":"volutpat","diets":"mauris sit","paymentMethods":"diners-club-enroute","atmosphere":"erat","extras":{"id":39,"name":"happyhour"},"room":"hall","active":false},
{"_id":"b19238ac-18ca-4dbc-8f8d-0d60cd99eb38","name":"Green Cockscomb","address":{"streetName":"3 Del Sol Plaza","streetNumber":"599","neighborhood":"Burning Wood","city":"Mar de Plata","state":"buenos aires","country":"Argentina","coordinates":{"latitud":-37.999834,"longitud":-57.555604}},"images":"http://dummyimage.com/164x100.png/ff4444/ffffff","contact":{"phoneNumber":"297-754-8933","email":"rkapelhof13@paginegialle.it","socialMedia":{"instagram":"eodonohue13@fotki.com","facebook":"jbulbrook13@jimdo.com","wpp":"hhaffard13@google.pl"}},"tables":40,"schedule":"10/21/2022","menu":"convallis","diets":"fermentum justo","paymentMethods":"jcb","atmosphere":"lacus","extras":{"id":40,"name":"happyhour"},"room":"terrace","active":true},
{"_id":"19c61e0e-e19b-4405-b321-84529b876cf6","name":"Waihee Valley Cyanea","address":{"streetName":"67 Emmet Road","streetNumber":"8","neighborhood":"Gulseth","city":"Mar de Plata","state":"buenos aires","country":"Argentina","coordinates":{"latitud":-37.997515,"longitud":-57.548015}},"images":"http://dummyimage.com/153x100.png/ff4444/ffffff","contact":{"phoneNumber":"359-888-5944","email":"jrycroft14@uiuc.edu","socialMedia":{"instagram":"ndibbe14@weibo.com","facebook":"btroy14@wordpress.com","wpp":"chyland14@archive.org"}},"tables":41,"schedule":"10/24/2022","menu":"mauris","diets":"nulla facilisi","paymentMethods":"diners-club-enroute","atmosphere":"ut","extras":{"id":41,"name":"petfriendly"},"room":"hall","active":true},
{"_id":"2f4bf9bf-599f-4ada-808f-45e7ae666f56","name":"Funeral Mountain Blue-eyed Grass","address":{"streetName":"70860 Montana Street","streetNumber":"32","neighborhood":"Clyde Gallagher","city":"Mar de Plata","state":"buenos aires","country":"Argentina","coordinates":{"latitud":-37.989915,"longitud":-57.544609}},"images":"http://dummyimage.com/216x100.png/ff4444/ffffff","contact":{"phoneNumber":"162-845-1327","email":"bbalharry15@ucoz.ru","socialMedia":{"instagram":"apreddle15@reverbnation.com","facebook":"sedwardson15@photobucket.com","wpp":"rcollabine15@google.de"}},"tables":42,"schedule":"3/8/2023","menu":"mauris","diets":"ultrices erat","paymentMethods":"mastercard","atmosphere":"fusce","extras":{"id":42,"name":"smoke"},"room":"hall","active":false},
{"_id":"1bf92a89-9ba9-4b91-ace7-f860bfbe999a","name":"Oligotrichum Moss","address":{"streetName":"06952 Mcguire Drive","streetNumber":"0632","neighborhood":"Dennis","city":"Mar de Plata","state":"buenos aires","country":"Argentina","coordinates":{"latitud":-38.013741,"longitud":-57.568679}},"images":"http://dummyimage.com/122x100.png/ff4444/ffffff","contact":{"phoneNumber":"425-107-7351","email":"medmeads16@pagesperso-orange.fr","socialMedia":{"instagram":"bhosier16@people.com.cn","facebook":"jthome16@ask.com","wpp":"bbailiss16@flickr.com"}},"tables":43,"schedule":"5/24/2022","menu":"nonummy","diets":"libero rutrum","paymentMethods":"diners-club-international","atmosphere":"ipsum","extras":{"id":43,"name":"petfriendly"},"room":"outdoor","active":true},
{"_id":"1c330a3a-a5dc-4273-9f64-f732859d7d88","name":"Parry's Goldenrod","address":{"streetName":"258 Buell Pass","streetNumber":"6806","neighborhood":"Anzinger","city":"Mar de Plata","state":"buenos aires","country":"Argentina","coordinates":{"latitud":-38.005825,"longitud":-57.559148}},"images":"http://dummyimage.com/181x100.png/5fa2dd/ffffff","contact":{"phoneNumber":"200-119-2286","email":"cgallahue17@foxnews.com","socialMedia":{"instagram":"ogomersal17@economist.com","facebook":"pannatt17@vistaprint.com","wpp":"tstanmore17@shinystat.com"}},"tables":44,"schedule":"10/24/2022","menu":"quisque","diets":"justo in","paymentMethods":"jcb","atmosphere":"nisi","extras":{"id":44,"name":"happyhour"},"room":"outdoor","active":true},
{"_id":"b328ef0d-0a35-4a7b-9757-79f26510af5e","name":"Field Sagewort","address":{"streetName":"96 Johnson Court","streetNumber":"46904","neighborhood":"Magdeline","city":"Mar de Plata","state":"buenos aires","country":"Argentina","coordinates":{"latitud":-38.009579,"longitud":-57.561607}},"images":"http://dummyimage.com/186x100.png/dddddd/000000","contact":{"phoneNumber":"492-757-1657","email":"grenard18@posterous.com","socialMedia":{"instagram":"borteu18@statcounter.com","facebook":"nspurdle18@globo.com","wpp":"cmcartan18@ucsd.edu"}},"tables":45,"schedule":"7/21/2022","menu":"leo","diets":"odio justo","paymentMethods":"switch","atmosphere":"eget","extras":{"id":45,"name":"petfriendly"},"room":"hall","active":true},
{"_id":"9ced548b-e9f4-4074-8fea-dbb38a36dc8b","name":"Solorinella Lichen","address":{"streetName":"3 Atwood Parkway","streetNumber":"66893","neighborhood":"Harper","city":"Mar de Plata","state":"buenos aires","country":"Argentina","coordinates":{"latitud":-38.015986,"longitud":-57.566279}},"images":"http://dummyimage.com/185x100.png/ff4444/ffffff","contact":{"phoneNumber":"586-313-8644","email":"cschrei19@skyrock.com","socialMedia":{"instagram":"fprestige19@mapy.cz","facebook":"azima19@tamu.edu","wpp":"fmckay19@vistaprint.com"}},"tables":46,"schedule":"2/15/2023","menu":"dui","diets":"interdum eu","paymentMethods":"solo","atmosphere":"suspendisse","extras":{"id":46,"name":"petfriendly"},"room":"terrace","active":true},
{"_id":"eb5eade7-6af8-4e6f-8cb7-7fd4cc90c477","name":"Leprevost's Helminthocarpon Lichen","address":{"streetName":"495 Leroy Park","streetNumber":"0","neighborhood":"Homewood","city":"Mar de Plata","state":"buenos aires","country":"Argentina","coordinates":{"latitud":-37.992485,"longitud":-57.545913}},"images":"http://dummyimage.com/232x100.png/ff4444/ffffff","contact":{"phoneNumber":"624-727-6972","email":"fhosier1a@sun.com","socialMedia":{"instagram":"acobson1a@bloglovin.com","facebook":"cpresho1a@nps.gov","wpp":"uwalworche1a@ow.ly"}},"tables":47,"schedule":"2/4/2023","menu":"nulla","diets":"duis faucibus","paymentMethods":"jcb","atmosphere":"interdum","extras":{"id":47,"name":"happyhour"},"room":"hall","active":false},
{"_id":"6f45bfd9-98e1-4c72-9303-d1025cfec135","name":"Haya","address":{"streetName":"08 Green Avenue","streetNumber":"61","neighborhood":"Lukken","city":"Mar de Plata","state":"buenos aires","country":"Argentina","coordinates":{"latitud":-37.997163,"longitud":-57.564534}},"images":"http://dummyimage.com/132x100.png/cc0000/ffffff","contact":{"phoneNumber":"794-892-1933","email":"adeam1b@icio.us","socialMedia":{"instagram":"mboliver1b@msu.edu","facebook":"thaseman1b@cbc.ca","wpp":"klandells1b@europa.eu"}},"tables":48,"schedule":"1/1/2023","menu":"orci","diets":"et ultrices","paymentMethods":"bankcard","atmosphere":"nisi","extras":{"id":48,"name":"petfriendly"},"room":"hall","active":true},
{"_id":"b38167b9-f65a-4b5d-8745-03050046e815","name":"Jelly Lichen","address":{"streetName":"75 Lakewood Hill","streetNumber":"1","neighborhood":"Grim","city":"Mar de Plata","state":"buenos aires","country":"Argentina","coordinates":{"latitud":-38.019907,"longitud":-57.543545}},"images":"http://dummyimage.com/180x100.png/5fa2dd/ffffff","contact":{"phoneNumber":"796-467-5992","email":"llicence1c@gov.uk","socialMedia":{"instagram":"nstallibrass1c@paginegialle.it","facebook":"qheinzel1c@alexa.com","wpp":"ckopmann1c@pagesperso-orange.fr"}},"tables":49,"schedule":"11/20/2022","menu":"nibh","diets":"in quam","paymentMethods":"switch","atmosphere":"mauris","extras":{"id":49,"name":"happyhour"},"room":"outdoor","active":true},
{"_id":"12b2687f-f3fb-4aae-915d-00dc8f88ae25","name":"Variegated Scouringrush","address":{"streetName":"75663 Pawling Parkway","streetNumber":"309","neighborhood":"Summer Ridge","city":"Mar de Plata","state":"buenos aires","country":"Argentina","coordinates":{"latitud":-37.990142,"longitud":-57.545963}},"images":"http://dummyimage.com/127x100.png/cc0000/ffffff","contact":{"phoneNumber":"325-887-9825","email":"dllopis1d@foxnews.com","socialMedia":{"instagram":"spozer1d@pen.io","facebook":"klackie1d@forbes.com","wpp":"eblincko1d@irs.gov"}},"tables":50,"schedule":"8/1/2022","menu":"eget","diets":"nec nisi","paymentMethods":"jcb","atmosphere":"in","extras":{"id":50,"name":"happyhour"},"room":"outdoor","active":true},
{"_id":"1a860465-71ee-47bd-9598-aa90ce908cde","name":"Lathberry","address":{"streetName":"3476 Little Fleur Trail","streetNumber":"2","neighborhood":"Grasskamp","city":"Mar de Plata","state":"buenos aires","country":"Argentina","coordinates":{"latitud":-38.009232,"longitud":-57.563358}},"images":"http://dummyimage.com/222x100.png/5fa2dd/ffffff","contact":{"phoneNumber":"759-545-5654","email":"gberesford1e@icio.us","socialMedia":{"instagram":"acrocker1e@who.int","facebook":"ndaile1e@fastcompany.com","wpp":"jdevuyst1e@github.com"}},"tables":51,"schedule":"11/16/2022","menu":"quis","diets":"sit amet","paymentMethods":"jcb","atmosphere":"eros","extras":{"id":51,"name":"petfriendly"},"room":"hall","active":false},
{"_id":"59bdf448-0f09-4fe0-bc4b-81abdeb95906","name":"Kopiko 'ula","address":{"streetName":"9 Erie Terrace","streetNumber":"950","neighborhood":"Elka","city":"Mar de Plata","state":"buenos aires","country":"Argentina","coordinates":{"latitud":-37.998701,"longitud":-57.544602}},"images":"http://dummyimage.com/247x100.png/dddddd/000000","contact":{"phoneNumber":"221-808-6725","email":"jspiring1f@pbs.org","socialMedia":{"instagram":"atroni1f@msu.edu","facebook":"wrepp1f@youtube.com","wpp":"ifatscher1f@ocn.ne.jp"}},"tables":52,"schedule":"9/14/2022","menu":"nunc","diets":"mauris non","paymentMethods":"diners-club-international","atmosphere":"justo","extras":{"id":52,"name":"smoke"},"room":"outdoor","active":false},
{"_id":"53109f1d-366b-4668-b771-0067515a3475","name":"Small Twistedstalk","address":{"streetName":"72 Pankratz Point","streetNumber":"91796","neighborhood":"Dapin","city":"Mar de Plata","state":"buenos aires","country":"Argentina","coordinates":{"latitud":-37.986708,"longitud":-57.549942}},"images":"http://dummyimage.com/189x100.png/5fa2dd/ffffff","contact":{"phoneNumber":"112-292-4975","email":"bkearle1g@tripadvisor.com","socialMedia":{"instagram":"jgiacubo1g@myspace.com","facebook":"dpoyner1g@cdbaby.com","wpp":"aprentice1g@hatena.ne.jp"}},"tables":53,"schedule":"6/15/2022","menu":"eget","diets":"volutpat erat","paymentMethods":"jcb","atmosphere":"nunc","extras":{"id":53,"name":"happyhour"},"room":"hall","active":false},
{"_id":"6132b7af-215e-4fd4-a65c-d61127fad3f4","name":"American Common Reed","address":{"streetName":"2791 Westend Lane","streetNumber":"6391","neighborhood":"Bartelt","city":"Mar de Plata","state":"buenos aires","country":"Argentina","coordinates":{"latitud":-37.998829,"longitud":-57.555758}},"images":"http://dummyimage.com/201x100.png/cc0000/ffffff","contact":{"phoneNumber":"268-882-2097","email":"jstiling1h@pen.io","socialMedia":{"instagram":"emacturlough1h@goodreads.com","facebook":"hshimon1h@cnn.com","wpp":"styre1h@edublogs.org"}},"tables":54,"schedule":"12/14/2022","menu":"pellentesque","diets":"rutrum nulla","paymentMethods":"visa","atmosphere":"maecenas","extras":{"id":54,"name":"petfriendly"},"room":"outdoor","active":true},
{"_id":"7fec7700-dc74-44e4-978c-bc9e33a9926b","name":"Synedrella","address":{"streetName":"64 Lyons Parkway","streetNumber":"85155","neighborhood":"Corscot","city":"Mar de Plata","state":"buenos aires","country":"Argentina","coordinates":{"latitud":-37.997601,"longitud":-57.557351}},"images":"http://dummyimage.com/118x100.png/cc0000/ffffff","contact":{"phoneNumber":"809-265-3480","email":"eallberry1i@chronoengine.com","socialMedia":{"instagram":"ncurado1i@sphinn.com","facebook":"aausher1i@webnode.com","wpp":"msauvain1i@oracle.com"}},"tables":55,"schedule":"8/26/2022","menu":"pede","diets":"pede justo","paymentMethods":"mastercard","atmosphere":"enim","extras":{"id":55,"name":"happyhour"},"room":"bar","active":false},
{"_id":"a511ff66-e2de-4151-a02c-02288d5482e8","name":"Texas Milkweed","address":{"streetName":"01 Debs Terrace","streetNumber":"26","neighborhood":"Rigney","city":"Mar de Plata","state":"buenos aires","country":"Argentina","coordinates":{"latitud":-38.004873,"longitud":-57.561708}},"images":"http://dummyimage.com/227x100.png/5fa2dd/ffffff","contact":{"phoneNumber":"388-974-5975","email":"tglyssanne1j@sciencedaily.com","socialMedia":{"instagram":"joveral1j@redcross.org","facebook":"gmarchington1j@ocn.ne.jp","wpp":"abenezeit1j@vkontakte.ru"}},"tables":56,"schedule":"5/26/2022","menu":"nam","diets":"parturient montes","paymentMethods":"mastercard","atmosphere":"consectetuer","extras":{"id":56,"name":"petfriendly"},"room":"terrace","active":false},
{"_id":"c09a41b6-e399-4615-a6cb-38011bc7f6e3","name":"Bald Brome","address":{"streetName":"949 David Parkway","streetNumber":"730","neighborhood":"Carpenter","city":"Mar de Plata","state":"buenos aires","country":"Argentina","coordinates":{"latitud":-38.00489,"longitud":-57.564127}},"images":"http://dummyimage.com/210x100.png/cc0000/ffffff","contact":{"phoneNumber":"388-392-3214","email":"ihadwin1k@dyndns.org","socialMedia":{"instagram":"ldeverson1k@weather.com","facebook":"mcaldaro1k@tuttocitta.it","wpp":"mblinder1k@bloglines.com"}},"tables":57,"schedule":"2/6/2023","menu":"odio","diets":"ante ipsum","paymentMethods":"jcb","atmosphere":"nunc","extras":{"id":57,"name":"petfriendly"},"room":"hall","active":false},
{"_id":"4770e453-8277-4087-875a-349241494de5","name":"Hollyberry Cotoneaster","address":{"streetName":"3421 Nancy Park","streetNumber":"02","neighborhood":"Lotheville","city":"Mar de Plata","state":"buenos aires","country":"Argentina","coordinates":{"latitud":-37.987948,"longitud":-57.566331}},"images":"http://dummyimage.com/155x100.png/dddddd/000000","contact":{"phoneNumber":"424-778-1069","email":"rberdale1l@artisteer.com","socialMedia":{"instagram":"cwakelam1l@baidu.com","facebook":"sshimwell1l@rambler.ru","wpp":"fhousley1l@hp.com"}},"tables":58,"schedule":"3/26/2022","menu":"non","diets":"et commodo","paymentMethods":"bankcard","atmosphere":"volutpat","extras":{"id":58,"name":"smoke"},"room":"outdoor","active":false},
{"_id":"4c2bd53c-ef4b-4bff-aa87-d81af51a8d0a","name":"Wheeler's Disc Lichen","address":{"streetName":"212 Maryland Parkway","streetNumber":"55813","neighborhood":"Grover","city":"Mar de Plata","state":"buenos aires","country":"Argentina","coordinates":{"latitud":-38.018479,"longitud":-57.544099}},"images":"http://dummyimage.com/221x100.png/cc0000/ffffff","contact":{"phoneNumber":"350-855-9058","email":"gmenear1m@smugmug.com","socialMedia":{"instagram":"dcapron1m@dot.gov","facebook":"jkemmet1m@google.co.jp","wpp":"cbretherton1m@who.int"}},"tables":59,"schedule":"3/7/2023","menu":"tincidunt","diets":"libero nam","paymentMethods":"jcb","atmosphere":"ut","extras":{"id":59,"name":"happyhour"},"room":"terrace","active":true},
{"_id":"196bd1fe-6817-421a-af91-ca9068275f16","name":"Nerveless Woodland Sedge","address":{"streetName":"9363 Shelley Crossing","streetNumber":"5","neighborhood":"Hintze","city":"Mar de Plata","state":"buenos aires","country":"Argentina","coordinates":{"latitud":-38.007354,"longitud":-57.571388}},"images":"http://dummyimage.com/168x100.png/dddddd/000000","contact":{"phoneNumber":"646-269-6678","email":"spilkington1n@indiatimes.com","socialMedia":{"instagram":"binkles1n@newsvine.com","facebook":"yleighton1n@gnu.org","wpp":"kerdis1n@tinypic.com"}},"tables":60,"schedule":"4/27/2022","menu":"amet","diets":"mattis egestas","paymentMethods":"americanexpress","atmosphere":"viverra","extras":{"id":60,"name":"happyhour"},"room":"outdoor","active":true},
{"_id":"22ed5b5b-653c-4c61-b29f-4b379196641b","name":"Rosemary-mint","address":{"streetName":"75 Moulton Parkway","streetNumber":"889","neighborhood":"Jenifer","city":"Mar de Plata","state":"buenos aires","country":"Argentina","coordinates":{"latitud":-38.01289,"longitud":-57.56571}},"images":"http://dummyimage.com/213x100.png/5fa2dd/ffffff","contact":{"phoneNumber":"315-364-8501","email":"bletessier1o@simplemachines.org","socialMedia":{"instagram":"jashard1o@shop-pro.jp","facebook":"wlove1o@diigo.com","wpp":"nwaleworke1o@admin.ch"}},"tables":61,"schedule":"7/18/2022","menu":"donec","diets":"at nunc","paymentMethods":"jcb","atmosphere":"et","extras":{"id":61,"name":"happyhour"},"room":"outdoor","active":true},
{"_id":"f318d926-17c1-4646-b6df-841e0e3c2e92","name":"Cliff Muhly","address":{"streetName":"6 Nobel Terrace","streetNumber":"298","neighborhood":"Florence","city":"Mar de Plata","state":"buenos aires","country":"Argentina","coordinates":{"latitud":-38.00726,"longitud":-57.557338}},"images":"http://dummyimage.com/111x100.png/ff4444/ffffff","contact":{"phoneNumber":"443-240-0957","email":"eroycraft1p@plala.or.jp","socialMedia":{"instagram":"mheatherington1p@nytimes.com","facebook":"mmcgovern1p@vinaora.com","wpp":"wabel1p@sourceforge.net"}},"tables":62,"schedule":"1/1/2023","menu":"augue","diets":"rutrum rutrum","paymentMethods":"jcb","atmosphere":"feugiat","extras":{"id":62,"name":"petfriendly"},"room":"terrace","active":false},
{"_id":"b3920a4d-0293-4b5d-9b27-5b74b1ba3f5f","name":"Ceanothus","address":{"streetName":"74 Crownhardt Trail","streetNumber":"769","neighborhood":"Pennsylvania","city":"Mar de Plata","state":"buenos aires","country":"Argentina","coordinates":{"latitud":-38.010817,"longitud":-57.551907}},"images":"http://dummyimage.com/180x100.png/dddddd/000000","contact":{"phoneNumber":"328-715-5391","email":"mmainstone1q@oaic.gov.au","socialMedia":{"instagram":"jdegogay1q@noaa.gov","facebook":"eanyene1q@archive.org","wpp":"adrinkel1q@acquirethisname.com"}},"tables":63,"schedule":"2/17/2023","menu":"id","diets":"nam ultrices","paymentMethods":"diners-club-international","atmosphere":"id","extras":{"id":63,"name":"smoke"},"room":"bar","active":false},
{"_id":"9a078f8a-9a4b-4187-bc9f-3b3bfb389857","name":"Waianae Range Tetramolopium","address":{"streetName":"0 Hoepker Avenue","streetNumber":"83","neighborhood":"Alpine","city":"Mar de Plata","state":"buenos aires","country":"Argentina","coordinates":{"latitud":-37.993554,"longitud":-57.554722}},"images":"http://dummyimage.com/190x100.png/ff4444/ffffff","contact":{"phoneNumber":"773-128-0071","email":"fbalassa1r@geocities.jp","socialMedia":{"instagram":"nzylbermann1r@cloudflare.com","facebook":"cfilipowicz1r@amazon.de","wpp":"losheils1r@google.com.au"}},"tables":64,"schedule":"9/4/2022","menu":"dui","diets":"donec odio","paymentMethods":"jcb","atmosphere":"duis","extras":{"id":64,"name":"happyhour"},"room":"bar","active":false},
{"_id":"427a3dcf-0413-40bf-ba6f-12b8b58bc434","name":"Macrothelypteris","address":{"streetName":"38850 Stuart Crossing","streetNumber":"707","neighborhood":"Garrison","city":"Mar de Plata","state":"buenos aires","country":"Argentina","coordinates":{"latitud":-38.008749,"longitud":-57.561472}},"images":"http://dummyimage.com/214x100.png/cc0000/ffffff","contact":{"phoneNumber":"664-199-9606","email":"phiggen1s@wiley.com","socialMedia":{"instagram":"fdunmuir1s@eventbrite.com","facebook":"tengall1s@friendfeed.com","wpp":"schrippes1s@oakley.com"}},"tables":65,"schedule":"6/24/2022","menu":"donec","diets":"semper sapien","paymentMethods":"jcb","atmosphere":"in","extras":{"id":65,"name":"smoke"},"room":"hall","active":true},
{"_id":"445a34b2-6e20-4aa7-bf4c-7b71ef5f6044","name":"Pussyfoot","address":{"streetName":"2 Delladonna Lane","streetNumber":"73824","neighborhood":"Mariners Cove","city":"Mar de Plata","state":"buenos aires","country":"Argentina","coordinates":{"latitud":-38.009844,"longitud":-57.552568}},"images":"http://dummyimage.com/226x100.png/cc0000/ffffff","contact":{"phoneNumber":"173-987-0719","email":"lscrivenor1t@arstechnica.com","socialMedia":{"instagram":"toaten1t@people.com.cn","facebook":"sduffill1t@intel.com","wpp":"svanarsdale1t@businesswire.com"}},"tables":66,"schedule":"8/1/2022","menu":"risus","diets":"dui vel","paymentMethods":"jcb","atmosphere":"in","extras":{"id":66,"name":"petfriendly"},"room":"Indoor","active":false},
{"_id":"01bde743-c519-4c47-819c-074d95cc813e","name":"Mediterranean Rabbitsfoot Grass","address":{"streetName":"5 Hermina Avenue","streetNumber":"21","neighborhood":"Little Fleur","city":"Mar de Plata","state":"buenos aires","country":"Argentina","coordinates":{"latitud":-38.01481,"longitud":-57.562034}},"images":"http://dummyimage.com/168x100.png/cc0000/ffffff","contact":{"phoneNumber":"562-862-9385","email":"wnewcom1u@unicef.org","socialMedia":{"instagram":"npevsner1u@hao123.com","facebook":"harpe1u@bravesites.com","wpp":"jseamark1u@youtube.com"}},"tables":67,"schedule":"11/13/2022","menu":"quam","diets":"lobortis est","paymentMethods":"mastercard","atmosphere":"a","extras":{"id":67,"name":"petfriendly"},"room":"Indoor","active":false},
{"_id":"5ff1775b-2373-4d64-abcd-7f93452423f0","name":"Arroyo Willow","address":{"streetName":"4 Laurel Crossing","streetNumber":"2","neighborhood":"Cody","city":"Mar de Plata","state":"buenos aires","country":"Argentina","coordinates":{"latitud":-38.008743,"longitud":-57.547104}},"images":"http://dummyimage.com/127x100.png/cc0000/ffffff","contact":{"phoneNumber":"521-236-1537","email":"fyushin1v@princeton.edu","socialMedia":{"instagram":"mfriett1v@feedburner.com","facebook":"mhakey1v@wikimedia.org","wpp":"mgilhouley1v@prlog.org"}},"tables":68,"schedule":"7/11/2022","menu":"ut","diets":"sit amet","paymentMethods":"switch","atmosphere":"viverra","extras":{"id":68,"name":"smoke"},"room":"terrace","active":false},
{"_id":"beff7f02-50c6-46af-abd4-8f2bfaf560fa","name":"Nodding Locoweed","address":{"streetName":"5 South Pass","streetNumber":"35722","neighborhood":"Transport","city":"Mar de Plata","state":"buenos aires","country":"Argentina","coordinates":{"latitud":-38.0101,"longitud":-57.569109}},"images":"http://dummyimage.com/173x100.png/ff4444/ffffff","contact":{"phoneNumber":"844-573-1597","email":"pglassard1w@cbc.ca","socialMedia":{"instagram":"ptellenbrok1w@oakley.com","facebook":"hgovinlock1w@mediafire.com","wpp":"tborthram1w@theglobeandmail.com"}},"tables":69,"schedule":"3/31/2022","menu":"et","diets":"dapibus augue","paymentMethods":"maestro","atmosphere":"natoque","extras":{"id":69,"name":"smoke"},"room":"Indoor","active":true},
{"_id":"f48217a4-ed6b-4d7b-a125-4004d10ed8a1","name":"Hawthorn","address":{"streetName":"44 Longview Way","streetNumber":"63","neighborhood":"Marquette","city":"Mar de Plata","state":"buenos aires","country":"Argentina","coordinates":{"latitud":-38.007153,"longitud":-57.570695}},"images":"http://dummyimage.com/190x100.png/cc0000/ffffff","contact":{"phoneNumber":"428-975-0123","email":"gwadlow1x@pcworld.com","socialMedia":{"instagram":"sbick1x@squarespace.com","facebook":"grappport1x@spiegel.de","wpp":"pwoolaghan1x@columbia.edu"}},"tables":70,"schedule":"6/24/2022","menu":"tristique","diets":"urna ut","paymentMethods":"jcb","atmosphere":"nam","extras":{"id":70,"name":"happyhour"},"room":"bar","active":true},
{"_id":"16853b62-1295-404f-8cae-da7929fc589d","name":"Clover","address":{"streetName":"04289 Spenser Circle","streetNumber":"05","neighborhood":"Clarendon","city":"Mar de Plata","state":"buenos aires","country":"Argentina","coordinates":{"latitud":-38.0037,"longitud":-57.567464}},"images":"http://dummyimage.com/232x100.png/cc0000/ffffff","contact":{"phoneNumber":"329-320-6134","email":"cchalcroft1y@guardian.co.uk","socialMedia":{"instagram":"jlipmann1y@cyberchimps.com","facebook":"hcuel1y@google.nl","wpp":"cshee1y@webnode.com"}},"tables":71,"schedule":"1/14/2023","menu":"nascetur","diets":"dictumst maecenas","paymentMethods":"jcb","atmosphere":"tincidunt","extras":{"id":71,"name":"happyhour"},"room":"hall","active":false},
{"_id":"9ae7f803-0a30-4450-8c53-b521adf3ec33","name":"Northern Slender Lady's Tresses","address":{"streetName":"6 Banding Center","streetNumber":"6","neighborhood":"Northridge","city":"Mar de Plata","state":"buenos aires","country":"Argentina","coordinates":{"latitud":-37.98376,"longitud":-57.542535}},"images":"http://dummyimage.com/207x100.png/ff4444/ffffff","contact":{"phoneNumber":"962-893-1799","email":"cmeacher1z@admin.ch","socialMedia":{"instagram":"tlinge1z@instagram.com","facebook":"ngeekin1z@skype.com","wpp":"sgrieg1z@businessinsider.com"}},"tables":72,"schedule":"4/30/2022","menu":"sollicitudin","diets":"amet eleifend","paymentMethods":"jcb","atmosphere":"sit","extras":{"id":72,"name":"petfriendly"},"room":"bar","active":true},
{"_id":"50458c8c-7bd7-4664-ae81-e69859054291","name":"Stalkless Yellowcress","address":{"streetName":"72 Steensland Parkway","streetNumber":"3","neighborhood":"Porter","city":"Mar de Plata","state":"buenos aires","country":"Argentina","coordinates":{"latitud":-37.995623,"longitud":-57.569579}},"images":"http://dummyimage.com/199x100.png/cc0000/ffffff","contact":{"phoneNumber":"534-696-5592","email":"abath20@prnewswire.com","socialMedia":{"instagram":"otembey20@phpbb.com","facebook":"mblanchet20@google.pl","wpp":"tbondesen20@goodreads.com"}},"tables":73,"schedule":"12/1/2022","menu":"nisi","diets":"praesent id","paymentMethods":"jcb","atmosphere":"lectus","extras":{"id":73,"name":"happyhour"},"room":"bar","active":false},
{"_id":"24a68b45-a547-4c14-a572-1c704d8f4359","name":"Dwarf Chinquapin Oak","address":{"streetName":"18417 Brentwood Junction","streetNumber":"9194","neighborhood":"Valley Edge","city":"Mar de Plata","state":"buenos aires","country":"Argentina","coordinates":{"latitud":-37.995299,"longitud":-57.558738}},"images":"http://dummyimage.com/240x100.png/ff4444/ffffff","contact":{"phoneNumber":"686-379-8110","email":"ahannigane21@dropbox.com","socialMedia":{"instagram":"falbarez21@jiathis.com","facebook":"eandreasen21@exblog.jp","wpp":"cplett21@theatlantic.com"}},"tables":74,"schedule":"11/11/2022","menu":"ligula","diets":"libero nam","paymentMethods":"laser","atmosphere":"proin","extras":{"id":74,"name":"happyhour"},"room":"Indoor","active":false},
{"_id":"892c915a-b84c-4b1c-89d3-fbbc6224c785","name":"Florida Orangegrass","address":{"streetName":"704 Eagan Plaza","streetNumber":"91","neighborhood":"Melvin","city":"Mar de Plata","state":"buenos aires","country":"Argentina","coordinates":{"latitud":-37.996865,"longitud":-57.561307}},"images":"http://dummyimage.com/227x100.png/cc0000/ffffff","contact":{"phoneNumber":"771-100-6024","email":"jbraunds22@kickstarter.com","socialMedia":{"instagram":"kmoscon22@seattletimes.com","facebook":"aprawle22@google.it","wpp":"lderby22@fda.gov"}},"tables":75,"schedule":"1/15/2023","menu":"vulputate","diets":"faucibus cursus","paymentMethods":"americanexpress","atmosphere":"amet","extras":{"id":75,"name":"petfriendly"},"room":"outdoor","active":true},
{"_id":"9b640dc7-63c7-4f0f-ba0a-4e2efdbd2a9f","name":"Beyrich's Hooded Orchid","address":{"streetName":"674 Paget Avenue","streetNumber":"01","neighborhood":"Ludington","city":"Mar de Plata","state":"buenos aires","country":"Argentina","coordinates":{"latitud":-37.985486,"longitud":-57.562567}},"images":"http://dummyimage.com/204x100.png/5fa2dd/ffffff","contact":{"phoneNumber":"628-375-5384","email":"gspringford23@mapy.cz","socialMedia":{"instagram":"aheugh23@miitbeian.gov.cn","facebook":"fcaswell23@cdbaby.com","wpp":"rmathet23@discuz.net"}},"tables":76,"schedule":"11/1/2022","menu":"platea","diets":"ipsum primis","paymentMethods":"diners-club-us-ca","atmosphere":"odio","extras":{"id":76,"name":"smoke"},"room":"terrace","active":true},
{"_id":"9c127e3d-fc7b-4f0b-be19-43a32238772e","name":"Warty Sedge","address":{"streetName":"6705 Fairview Avenue","streetNumber":"8308","neighborhood":"Dwight","city":"Mar de Plata","state":"buenos aires","country":"Argentina","coordinates":{"latitud":-37.996123,"longitud":-57.568629}},"images":"http://dummyimage.com/222x100.png/5fa2dd/ffffff","contact":{"phoneNumber":"449-683-5598","email":"kbubear24@flavors.me","socialMedia":{"instagram":"ctorr24@indiegogo.com","facebook":"bcharpin24@bing.com","wpp":"mgristwood24@xrea.com"}},"tables":77,"schedule":"6/25/2022","menu":"platea","diets":"at turpis","paymentMethods":"visa","atmosphere":"nec","extras":{"id":77,"name":"petfriendly"},"room":"terrace","active":false},
{"_id":"3b89104a-332a-47f3-b99e-03de04a84c72","name":"Horsehair Lichen","address":{"streetName":"999 Blackbird Drive","streetNumber":"6","neighborhood":"Mendota","city":"Mar de Plata","state":"buenos aires","country":"Argentina","coordinates":{"latitud":-38.010701,"longitud":-57.568461}},"images":"http://dummyimage.com/112x100.png/cc0000/ffffff","contact":{"phoneNumber":"666-309-7931","email":"ywattisham25@java.com","socialMedia":{"instagram":"bkantor25@blogs.com","facebook":"bskein25@desdev.cn","wpp":"acanepe25@cbslocal.com"}},"tables":78,"schedule":"1/26/2023","menu":"nulla","diets":"nascetur ridiculus","paymentMethods":"jcb","atmosphere":"risus","extras":{"id":78,"name":"happyhour"},"room":"Indoor","active":true},
{"_id":"b499a010-1c2f-4b87-99e7-bb383581fd3c","name":"Strigose Beard Lichen","address":{"streetName":"865 Birchwood Park","streetNumber":"0","neighborhood":"Parkside","city":"Mar de Plata","state":"buenos aires","country":"Argentina","coordinates":{"latitud":-37.99712,"longitud":-57.554413}},"images":"http://dummyimage.com/205x100.png/5fa2dd/ffffff","contact":{"phoneNumber":"423-209-2763","email":"ufolcarelli26@live.com","socialMedia":{"instagram":"ngreetland26@skype.com","facebook":"rbonellie26@theguardian.com","wpp":"skilloran26@slate.com"}},"tables":79,"schedule":"3/6/2023","menu":"phasellus","diets":"ut ultrices","paymentMethods":"jcb","atmosphere":"lorem","extras":{"id":79,"name":"petfriendly"},"room":"bar","active":false},
{"_id":"c651797e-91f0-4541-9262-641ce430fd99","name":"Soft Bindweed","address":{"streetName":"618 Hoffman Place","streetNumber":"36","neighborhood":"Waywood","city":"Mar de Plata","state":"buenos aires","country":"Argentina","coordinates":{"latitud":-37.986968,"longitud":-57.569763}},"images":"http://dummyimage.com/196x100.png/dddddd/000000","contact":{"phoneNumber":"387-219-3660","email":"chauxwell27@java.com","socialMedia":{"instagram":"mwiper27@ocn.ne.jp","facebook":"ksuart27@blogger.com","wpp":"tfeldberger27@bloglovin.com"}},"tables":80,"schedule":"7/16/2022","menu":"non","diets":"sapien urna","paymentMethods":"visa-electron","atmosphere":"rutrum","extras":{"id":80,"name":"smoke"},"room":"terrace","active":true},
{"_id":"b3af690e-1ed0-4980-8f87-22cb058e4ea5","name":"Cerebral Fishscale Lichen","address":{"streetName":"6 Spenser Park","streetNumber":"136","neighborhood":"Monica","city":"Mar de Plata","state":"buenos aires","country":"Argentina","coordinates":{"latitud":-37.994345,"longitud":-57.560719}},"images":"http://dummyimage.com/196x100.png/dddddd/000000","contact":{"phoneNumber":"931-737-9797","email":"nhusk28@qq.com","socialMedia":{"instagram":"jkitlee28@1688.com","facebook":"hgreatland28@tiny.cc","wpp":"rfasler28@mysql.com"}},"tables":81,"schedule":"9/18/2022","menu":"cubilia","diets":"nam dui","paymentMethods":"diners-club-carte-blanche","atmosphere":"fusce","extras":{"id":81,"name":"happyhour"},"room":"bar","active":false},
{"_id":"3505bf53-efb3-431b-a15c-78ff61664934","name":"Texas Cornsalad","address":{"streetName":"248 Huxley Plaza","streetNumber":"1489","neighborhood":"Pennsylvania","city":"Mar de Plata","state":"buenos aires","country":"Argentina","coordinates":{"latitud":-37.988886,"longitud":-57.56782}},"images":"http://dummyimage.com/131x100.png/cc0000/ffffff","contact":{"phoneNumber":"186-213-1111","email":"dlocock29@sfgate.com","socialMedia":{"instagram":"gsnelling29@yelp.com","facebook":"pgoldney29@themeforest.net","wpp":"nbluett29@opensource.org"}},"tables":82,"schedule":"6/20/2022","menu":"turpis","diets":"enim in","paymentMethods":"jcb","atmosphere":"maecenas","extras":{"id":82,"name":"petfriendly"},"room":"hall","active":false},
{"_id":"5ef9f9b1-11df-45f8-adfa-329c98e8db62","name":"Creeping Lady's Nightcap","address":{"streetName":"68360 Bonner Crossing","streetNumber":"01","neighborhood":"Old Gate","city":"Mar de Plata","state":"buenos aires","country":"Argentina","coordinates":{"latitud":-37.988818,"longitud":-57.557519}},"images":"http://dummyimage.com/167x100.png/5fa2dd/ffffff","contact":{"phoneNumber":"897-480-5479","email":"dkelwaybamber2a@ebay.co.uk","socialMedia":{"instagram":"rbonin2a@squidoo.com","facebook":"ndeye2a@scientificamerican.com","wpp":"fpandya2a@oracle.com"}},"tables":83,"schedule":"4/22/2022","menu":"penatibus","diets":"eleifend donec","paymentMethods":"maestro","atmosphere":"lorem","extras":{"id":83,"name":"smoke"},"room":"terrace","active":true},
{"_id":"62302209-7647-4a58-942c-c81f12c6f19e","name":"Orthotrichum Moss","address":{"streetName":"650 Northview Way","streetNumber":"587","neighborhood":"Blue Bill Park","city":"Mar de Plata","state":"buenos aires","country":"Argentina","coordinates":{"latitud":-37.998265,"longitud":-57.549916}},"images":"http://dummyimage.com/197x100.png/5fa2dd/ffffff","contact":{"phoneNumber":"912-278-5831","email":"bbanville2b@tinypic.com","socialMedia":{"instagram":"elarose2b@auda.org.au","facebook":"ocalltone2b@typepad.com","wpp":"nkirkebye2b@csmonitor.com"}},"tables":84,"schedule":"1/24/2023","menu":"enim","diets":"nam congue","paymentMethods":"jcb","atmosphere":"donec","extras":{"id":84,"name":"happyhour"},"room":"hall","active":true},
{"_id":"583f9e7d-0b91-4404-8c9d-ee6c942e3ddc","name":"Striped Barbados Lily","address":{"streetName":"2 Anzinger Park","streetNumber":"4676","neighborhood":"Truax","city":"Mar de Plata","state":"buenos aires","country":"Argentina","coordinates":{"latitud":-38.019861,"longitud":-57.544022}},"images":"http://dummyimage.com/248x100.png/cc0000/ffffff","contact":{"phoneNumber":"447-814-9282","email":"bflippini2c@boston.com","socialMedia":{"instagram":"cmein2c@myspace.com","facebook":"atieraney2c@ftc.gov","wpp":"ldurward2c@mit.edu"}},"tables":85,"schedule":"2/23/2023","menu":"aliquam","diets":"viverra dapibus","paymentMethods":"jcb","atmosphere":"rutrum","extras":{"id":85,"name":"petfriendly"},"room":"Indoor","active":false},
{"_id":"adafab77-f4f9-4c45-9cf2-c1159e0e0390","name":"Panicled False Indigo","address":{"streetName":"0925 Clemons Avenue","streetNumber":"16","neighborhood":"Chive","city":"Mar de Plata","state":"buenos aires","country":"Argentina","coordinates":{"latitud":-37.997587,"longitud":-57.56688}},"images":"http://dummyimage.com/167x100.png/ff4444/ffffff","contact":{"phoneNumber":"436-659-8574","email":"bsproston2d@furl.net","socialMedia":{"instagram":"paldington2d@abc.net.au","facebook":"hdesvignes2d@vimeo.com","wpp":"ohansel2d@cnbc.com"}},"tables":86,"schedule":"1/1/2023","menu":"arcu","diets":"in libero","paymentMethods":"americanexpress","atmosphere":"amet","extras":{"id":86,"name":"petfriendly"},"room":"Indoor","active":false},
{"_id":"cbfc586d-e967-448c-9b2c-01ab8d5e681c","name":"Orange Lichen","address":{"streetName":"7 Glacier Hill Road","streetNumber":"84367","neighborhood":"Luster","city":"Mar de Plata","state":"buenos aires","country":"Argentina","coordinates":{"latitud":-38.012886,"longitud":-57.558822}},"images":"http://dummyimage.com/160x100.png/5fa2dd/ffffff","contact":{"phoneNumber":"596-648-3764","email":"kdalyiel2e@unblog.fr","socialMedia":{"instagram":"ldarrington2e@fc2.com","facebook":"awigfield2e@patch.com","wpp":"acarabine2e@rakuten.co.jp"}},"tables":87,"schedule":"6/17/2022","menu":"condimentum","diets":"vulputate justo","paymentMethods":"mastercard","atmosphere":"quisque","extras":{"id":87,"name":"petfriendly"},"room":"Indoor","active":false},
{"_id":"29ec1d02-aba4-4845-b577-1ea54bbbdd6e","name":"Field Sagewort","address":{"streetName":"3 Reindahl Hill","streetNumber":"3","neighborhood":"Clyde Gallagher","city":"Mar de Plata","state":"buenos aires","country":"Argentina","coordinates":{"latitud":-38.01286,"longitud":-57.543961}},"images":"http://dummyimage.com/204x100.png/dddddd/000000","contact":{"phoneNumber":"181-563-7142","email":"qniset2f@hhs.gov","socialMedia":{"instagram":"wduddy2f@seesaa.net","facebook":"dfoote2f@spiegel.de","wpp":"btoombes2f@desdev.cn"}},"tables":88,"schedule":"11/22/2022","menu":"lobortis","diets":"mauris morbi","paymentMethods":"jcb","atmosphere":"platea","extras":{"id":88,"name":"petfriendly"},"room":"terrace","active":false},
{"_id":"8f52939c-3deb-4fcc-aec0-2b96ae24600e","name":"Wright's Saltbush","address":{"streetName":"10 North Avenue","streetNumber":"77","neighborhood":"Kedzie","city":"Mar de Plata","state":"buenos aires","country":"Argentina","coordinates":{"latitud":-38.009247,"longitud":-57.557067}},"images":"http://dummyimage.com/207x100.png/5fa2dd/ffffff","contact":{"phoneNumber":"916-802-8680","email":"iescreet2g@sitemeter.com","socialMedia":{"instagram":"nmcclosh2g@hugedomains.com","facebook":"ewegman2g@deviantart.com","wpp":"gleathe2g@sciencedaily.com"}},"tables":89,"schedule":"11/18/2022","menu":"neque","diets":"donec ut","paymentMethods":"diners-club-international","atmosphere":"et","extras":{"id":89,"name":"happyhour"},"room":"bar","active":false},
{"_id":"1fedc357-dc1f-4c17-83a4-b3d4ddf3d1bb","name":"Sand Ticktrefoil","address":{"streetName":"536 Anzinger Drive","streetNumber":"97482","neighborhood":"Blaine","city":"Mar de Plata","state":"buenos aires","country":"Argentina","coordinates":{"latitud":-37.995451,"longitud":-57.553193}},"images":"http://dummyimage.com/170x100.png/ff4444/ffffff","contact":{"phoneNumber":"696-509-5720","email":"rgrushin2h@noaa.gov","socialMedia":{"instagram":"ahaycroft2h@google.com","facebook":"fflode2h@facebook.com","wpp":"dcraghead2h@hao123.com"}},"tables":90,"schedule":"5/21/2022","menu":"habitasse","diets":"diam erat","paymentMethods":"diners-club-enroute","atmosphere":"potenti","extras":{"id":90,"name":"happyhour"},"room":"outdoor","active":false},
{"_id":"a8430d92-944c-4f57-aa0c-71c0b0cfee82","name":"Drepanocladus Moss","address":{"streetName":"84 Boyd Lane","streetNumber":"65992","neighborhood":"Rockefeller","city":"Mar de Plata","state":"buenos aires","country":"Argentina","coordinates":{"latitud":-37.987152,"longitud":-57.54532}},"images":"http://dummyimage.com/120x100.png/dddddd/000000","contact":{"phoneNumber":"512-919-9473","email":"bgowenlock2i@themeforest.net","socialMedia":{"instagram":"shellin2i@independent.co.uk","facebook":"jgladwell2i@github.com","wpp":"vhyndes2i@prnewswire.com"}},"tables":91,"schedule":"2/14/2023","menu":"metus","diets":"quisque porta","paymentMethods":"laser","atmosphere":"quam","extras":{"id":91,"name":"smoke"},"room":"hall","active":true},
{"_id":"26799e93-af32-4721-a531-d96637e9e497","name":"Florida Roseling","address":{"streetName":"1984 Dakota Crossing","streetNumber":"4","neighborhood":"Lotheville","city":"Mar de Plata","state":"buenos aires","country":"Argentina","coordinates":{"latitud":-38.011554,"longitud":-57.556225}},"images":"http://dummyimage.com/180x100.png/cc0000/ffffff","contact":{"phoneNumber":"158-622-2697","email":"kchatelot2j@phpbb.com","socialMedia":{"instagram":"hchampneys2j@pagesperso-orange.fr","facebook":"rdemangeon2j@printfriendly.com","wpp":"mwhiteland2j@opera.com"}},"tables":92,"schedule":"2/5/2023","menu":"auctor","diets":"nisl venenatis","paymentMethods":"jcb","atmosphere":"aliquam","extras":{"id":92,"name":"happyhour"},"room":"outdoor","active":true},
{"_id":"42d1f2f5-42f8-4556-930c-531b42c2fcdf","name":"Hypotrachyna Lichen","address":{"streetName":"79 Nelson Parkway","streetNumber":"35","neighborhood":"Meadow Vale","city":"Mar de Plata","state":"buenos aires","country":"Argentina","coordinates":{"latitud":-38.014584,"longitud":-57.570718}},"images":"http://dummyimage.com/123x100.png/cc0000/ffffff","contact":{"phoneNumber":"598-373-6212","email":"chandford2k@who.int","socialMedia":{"instagram":"tklauer2k@bloglovin.com","facebook":"dflescher2k@pcworld.com","wpp":"jmaith2k@delicious.com"}},"tables":93,"schedule":"12/24/2022","menu":"integer","diets":"libero ut","paymentMethods":"jcb","atmosphere":"id","extras":{"id":93,"name":"smoke"},"room":"Indoor","active":true},
{"_id":"106f599f-4dbe-4afc-8cba-27e35aa4a139","name":"Creeping Bishop's Cap","address":{"streetName":"0 Sunfield Street","streetNumber":"91","neighborhood":"Iowa","city":"Mar de Plata","state":"buenos aires","country":"Argentina","coordinates":{"latitud":-38.013093,"longitud":-57.556373}},"images":"http://dummyimage.com/103x100.png/dddddd/000000","contact":{"phoneNumber":"211-742-5140","email":"dhilldrop2l@unblog.fr","socialMedia":{"instagram":"sallom2l@360.cn","facebook":"hmitford2l@google.fr","wpp":"rsunock2l@google.fr"}},"tables":94,"schedule":"8/13/2022","menu":"sagittis","diets":"morbi sem","paymentMethods":"maestro","atmosphere":"at","extras":{"id":94,"name":"petfriendly"},"room":"hall","active":false},
{"_id":"9802595d-f60a-4e1d-9f21-9b619ea82551","name":"Virginia Bluebells","address":{"streetName":"757 Service Hill","streetNumber":"82617","neighborhood":"Commercial","city":"Mar de Plata","state":"buenos aires","country":"Argentina","coordinates":{"latitud":-37.988531,"longitud":-57.565416}},"images":"http://dummyimage.com/184x100.png/cc0000/ffffff","contact":{"phoneNumber":"354-552-8118","email":"ochitty2m@netlog.com","socialMedia":{"instagram":"efishley2m@nydailynews.com","facebook":"cmcguckin2m@biglobe.ne.jp","wpp":"rottewill2m@omniture.com"}},"tables":95,"schedule":"7/9/2022","menu":"curae","diets":"velit donec","paymentMethods":"jcb","atmosphere":"ac","extras":{"id":95,"name":"happyhour"},"room":"terrace","active":false},
{"_id":"b6c48def-123d-4bc0-80df-ea44fdef65cc","name":"Navajo Bridge Pricklypear","address":{"streetName":"00606 Shopko Circle","streetNumber":"6","neighborhood":"Barby","city":"Mar de Plata","state":"buenos aires","country":"Argentina","coordinates":{"latitud":-38.00962,"longitud":-57.543408}},"images":"http://dummyimage.com/140x100.png/ff4444/ffffff","contact":{"phoneNumber":"855-145-4224","email":"sschirak2n@jalbum.net","socialMedia":{"instagram":"enolin2n@oaic.gov.au","facebook":"vabbes2n@blogspot.com","wpp":"gaugust2n@jimdo.com"}},"tables":96,"schedule":"6/3/2022","menu":"ut","diets":"ultrices mattis","paymentMethods":"switch","atmosphere":"id","extras":{"id":96,"name":"petfriendly"},"room":"terrace","active":false},
{"_id":"ef966e96-5ee8-4299-af98-bf978ee1e053","name":"Williams' Buckwheat","address":{"streetName":"58 Vernon Hill","streetNumber":"2991","neighborhood":"Maywood","city":"Mar de Plata","state":"buenos aires","country":"Argentina","coordinates":{"latitud":-38.000218,"longitud":-57.552353}},"images":"http://dummyimage.com/157x100.png/ff4444/ffffff","contact":{"phoneNumber":"577-898-8199","email":"dmallows2o@cisco.com","socialMedia":{"instagram":"ccupper2o@cnbc.com","facebook":"dmcphater2o@fotki.com","wpp":"nschleswigholstein2o@weibo.com"}},"tables":97,"schedule":"7/15/2022","menu":"sed","diets":"non sodales","paymentMethods":"jcb","atmosphere":"amet","extras":{"id":97,"name":"petfriendly"},"room":"hall","active":false},
{"_id":"40b833f5-f7df-4f68-a989-084c6ffbdf31","name":"Small Matweed","address":{"streetName":"6 Farwell Lane","streetNumber":"47359","neighborhood":"Jay","city":"Mar de Plata","state":"buenos aires","country":"Argentina","coordinates":{"latitud":-38.014504,"longitud":-57.556679}},"images":"http://dummyimage.com/245x100.png/dddddd/000000","contact":{"phoneNumber":"862-274-0690","email":"jwheelhouse2p@mozilla.com","socialMedia":{"instagram":"bgason2p@accuweather.com","facebook":"jdossettor2p@mapquest.com","wpp":"abott2p@multiply.com"}},"tables":98,"schedule":"3/3/2023","menu":"est","diets":"odio curabitur","paymentMethods":"maestro","atmosphere":"mollis","extras":{"id":98,"name":"smoke"},"room":"outdoor","active":false},
{"_id":"e1ee22e6-666a-4903-8b9b-11d7309ebe6d","name":"Tonguefern","address":{"streetName":"81569 Saint Paul Center","streetNumber":"72498","neighborhood":"7th","city":"Mar de Plata","state":"buenos aires","country":"Argentina","coordinates":{"latitud":-37.999801,"longitud":-57.542934}},"images":"http://dummyimage.com/118x100.png/5fa2dd/ffffff","contact":{"phoneNumber":"285-763-9599","email":"etrevain2q@dailymail.co.uk","socialMedia":{"instagram":"cdrinan2q@123-reg.co.uk","facebook":"nfellgate2q@europa.eu","wpp":"bkenford2q@cmu.edu"}},"tables":99,"schedule":"2/20/2023","menu":"consectetuer","diets":"enim lorem","paymentMethods":"visa","atmosphere":"vehicula","extras":{"id":99,"name":"petfriendly"},"room":"hall","active":true},
{"_id":"16d9433f-c80c-4659-b4d3-380abaedee8e","name":"Snow Dwarf-primrose","address":{"streetName":"6834 Meadow Vale Plaza","streetNumber":"22350","neighborhood":"Carberry","city":"Mar de Plata","state":"buenos aires","country":"Argentina","coordinates":{"latitud":-38.014985,"longitud":-57.563227}},"images":"http://dummyimage.com/170x100.png/ff4444/ffffff","contact":{"phoneNumber":"801-993-1423","email":"elewens2r@altervista.org","socialMedia":{"instagram":"vheaps2r@umich.edu","facebook":"apothbury2r@imgur.com","wpp":"ituite2r@cdbaby.com"}},"tables":100,"schedule":"11/20/2022","menu":"eu","diets":"libero quis","paymentMethods":"jcb","atmosphere":"nunc","extras":{"id":100,"name":"petfriendly"},"room":"terrace","active":false}]